examples/__init__.py
examples/flat_project_example.py
examples/extending/__init__.py
examples/extending/camera_lens.py
examples/extending/great_entity.py
examples/extending/statused_entity.py
stalker/__init__.py
stalker/config.py
stalker/exceptions.py
stalker/log.py
stalker/testing.py
stalker/db/__init__.py
stalker/db/declarative.py
stalker/db/session.py
stalker/db/types.py
stalker/models/__init__.py
stalker/models/asset.py
stalker/models/auth.py
stalker/models/budget.py
stalker/models/client.py
stalker/models/department.py
stalker/models/entity.py
stalker/models/format.py
stalker/models/link.py
stalker/models/message.py
stalker/models/mixins.py
stalker/models/note.py
stalker/models/project.py
stalker/models/repository.py
stalker/models/review.py
stalker/models/scene.py
stalker/models/schedulers.py
stalker/models/sequence.py
stalker/models/shot.py
stalker/models/status.py
stalker/models/structure.py
stalker/models/studio.py
stalker/models/tag.py
stalker/models/task.py
stalker/models/template.py
stalker/models/ticket.py
stalker/models/type.py
stalker/models/version.py
stalker/models/wiki.py
stalker-0.2.28.data/data/COPYING
stalker-0.2.28.data/data/COPYING.LESSER
stalker-0.2.28.data/data/INSTALL
stalker-0.2.28.data/data/MANIFEST.in
stalker-0.2.28.data/data/README.rst
tests/__init__.py
tests/conftest.py
tests/test_exceptions.py
tests/test_readme_tutorial.py
tests/benchmarks/__init__.py
tests/benchmarks/task_total_logged_seonds.py
tests/config/__init__.py
tests/config/test_config.py
tests/db/__init__.py
tests/db/test_db.py
tests/mixins/__init__.py
tests/mixins/test_aclMixin.py
tests/mixins/test_amountMixin.py
tests/mixins/test_codeMixin.py
tests/mixins/test_dagMixin.py
tests/mixins/test_dateRangeMixin.py
tests/mixins/test_declarativeProjectMixin.py
tests/mixins/test_declarativeReferenceMixin.py
tests/mixins/test_declarativeScheduleMixin.py
tests/mixins/test_declarativeStatusMixin.py
tests/mixins/test_projectMixin.py
tests/mixins/test_referenceMixin.py
stalker-0.2.28.dist-info/LICENSE
stalker-0.2.28.dist-info/METADATA
stalker-0.2.28.dist-info/WHEEL
stalker-0.2.28.dist-info/top_level.txt
stalker-0.2.28.dist-info/zip-safe
stalker-0.2.28.dist-info/RECORD
