Metadata-Version: 2.1
Name: stalker
Version: 0.2.28
Summary: A Production Asset Management (ProdAM) System
Home-page: https://github.com/eoyilmaz/stalker
Author: Erkan Ozgur Yilmaz
Author-email: eoyilmaz@gmail.com
License: LGPLv3
Keywords: production,asset,management,vfx,animation,maya,houdini,nuke,fusion,softimage,blender,vue
Classifier: Programming Language :: Python
Classifier: Programming Language :: Python :: 2.7
Classifier: Programming Language :: Python :: 3.6
Classifier: Programming Language :: Python :: 3.7
Classifier: Programming Language :: Python :: 3.8
Classifier: Programming Language :: Python :: 3.9
Classifier: License :: OSI Approved :: GNU Lesser General Public License v3 (LGPLv3)
Classifier: Operating System :: OS Independent
Classifier: Development Status :: 5 - Production/Stable
Classifier: Intended Audience :: Developers
Classifier: Intended Audience :: End Users/Desktop
Classifier: Topic :: Database
Classifier: Topic :: Software Development
Classifier: Topic :: Utilities
Classifier: Topic :: Office/Business :: Scheduling
License-File: LICENSE
Requires-Dist: psycopg2-binary
Requires-Dist: sqlalchemy
Requires-Dist: alembic
Requires-Dist: jinja2
Requires-Dist: pytz
Requires-Dist: tzlocal
